mathext/__init__.py
mathext-0.2.1.dist-info/METADATA
mathext-0.2.1.dist-info/WHEEL
mathext-0.2.1.dist-info/top_level.txt
mathext-0.2.1.dist-info/RECORD
