Metadata-Version: 2.1
Name: mathext
Version: 0.2.1
Summary: An extension to the math library provided by Python.
Home-page: https://github.com/Richienb/mathext
Author: Richie Bendall
Author-email: richiebendall@gmail.com
License: MIT License
Platform: UNKNOWN
Classifier: Development Status :: 3 - Alpha
Classifier: Intended Audience :: Developers
Classifier: License :: OSI Approved :: MIT License
Classifier: Operating System :: OS Independent
Classifier: Natural Language :: English
Classifier: Topic :: Scientific/Engineering :: Mathematics
Classifier: Topic :: Security :: Cryptography
Classifier: Topic :: Software Development :: Libraries
Classifier: Programming Language :: Python
Classifier: Topic :: Software Development :: Libraries :: Python Modules
